{"hero":{"id":90101,"quality":6,"gender":0,"heroJobTree":1,"energyType":3,"type":2,"name":"라돈","title":"","jobDescribe":"","talentSummary":"없음","shenhuaGachaPainting":null,"specialPainting":null,"heroSkill":1,"defaultDress":7901010,"heroItem":0,"show":0,"isFriendshipOpen":0,"category":"npc","origin":"","characterClass":"?","factions":[106],"equipmentParts":[1,2,3,4,5,6],"heroJob":[],"worldIdleSkill":[],"generalAttack":[1],"atkSpd":1,"attackRadius":4.5,"speed":0,"attrTalent":[{"id":104,"value":1.1},{"id":304,"value":1.1},{"id":404,"value":1.1},{"id":504,"value":1.1},{"id":454,"value":1}],"mainPaintingUrl":null,"cardUrl":null,"rolePortraitUrl":null,"gachaBgUrl":"/img/79858faeb3049747123dea8fb34e8cec/Texture2D_bg_90101.webp","faceIconUrl":"/img/8da42b6460fa9c8811d0149f7694f68b/Sprite_icon_npc_90101_2.webp","favorabilityUrl":null,"harmonyUrl":null,"demonArtUrls":[],"backdropCandidates":["/img/79858faeb3049747123dea8fb34e8cec/Texture2D_bg_90101.webp"]},"profile":null,"starSkills":[],"gear":null,"skins":[{"id":7901010,"belongHero":90101,"isDefault":false,"name":"라돈","desc":"","quality":2,"cardAsset":"giant_1002","iconAsset":"icon_npc_90101_2","paintingAsset":"giant_1002","bgAsset":"bg_90101","harmonyCardAsset":null,"harmonyPaintingAsset":null,"harmonyBgAsset":"bg_90101","cardUrl":null,"isCurrent":true}],"skillsWithIcon":[]}