{"hero":{"id":91202,"quality":2,"gender":0,"heroJobTree":1,"energyType":0,"type":2,"name":"물 슬라임","title":"","jobDescribe":"","talentSummary":"없음","shenhuaGachaPainting":null,"specialPainting":null,"heroSkill":91202,"defaultDress":7912020,"heroItem":0,"show":0,"isFriendshipOpen":0,"category":"npc","origin":"","characterClass":"Guardian","factions":[106,104],"equipmentParts":[1,2,3,4,5,6],"heroJob":[],"worldIdleSkill":[99001,15023001],"generalAttack":[15023001],"atkSpd":1,"attackRadius":1.1,"speed":2.35,"attrTalent":[{"id":104,"value":0.89},{"id":304,"value":0.83},{"id":404,"value":0.88},{"id":504,"value":0.84},{"id":454,"value":1}],"mainPaintingUrl":"/img/63d0711f93f66fe6ae50941277c0271a/Texture2D_role_91202.webp","cardUrl":null,"rolePortraitUrl":"/img/63d0711f93f66fe6ae50941277c0271a/Texture2D_role_91202.webp","gachaBgUrl":"/img/350f72e0793866eb36f21af344d54056/Texture2D_bg_91202.webp","faceIconUrl":"/img/8da42b6460fa9c8811d0149f7694f68b/Sprite_icon_hero_91202.webp","favorabilityUrl":null,"harmonyUrl":null,"demonArtUrls":[],"backdropCandidates":["/img/350f72e0793866eb36f21af344d54056/Texture2D_bg_91202.webp"]},"profile":null,"starSkills":[{"id":9120201,"star":1,"shortDesc":"스킬 사용 후, 공격이 가장 높은 같은 진영 아군 영웅의 공격을 <color=#82c07f>100%</color> 증가하며, 5초 동안 지속되고 중첩되지 않는다.","fullDesc":"스킬 사용 후, 공격이 가장 높은 같은 진영 아군 영웅의 공격을 <color=#82c07f>100%</color> 증가하며, 5초 동안 지속되고 중첩되지 않는다.","talentSkill":12011,"ultraSkill":2},{"id":9120202,"star":2,"shortDesc":"스킬 사용 후, 공격이 가장 높은 같은 진영 아군 영웅의 공격을 <color=#82c07f>100%</color> 증가하며, 5초 동안 지속되고 중첩되지 않는다.","fullDesc":"스킬 사용 후, 공격이 가장 높은 같은 진영 아군 영웅의 공격을 <color=#82c07f>100%</color> 증가하며, 5초 동안 지속되고 중첩되지 않는다.","talentSkill":12011,"ultraSkill":2},{"id":9120203,"star":3,"shortDesc":"스킬 사용 후, 공격이 가장 높은 같은 진영 아군 영웅의 공격을 <color=#82c07f>100%</color> 증가하며, 5초 동안 지속되고 중첩되지 않는다.","fullDesc":"스킬 사용 후, 공격이 가장 높은 같은 진영 아군 영웅의 공격을 <color=#82c07f>100%</color> 증가하며, 5초 동안 지속되고 중첩되지 않는다.","talentSkill":12011,"ultraSkill":2},{"id":9120204,"star":4,"shortDesc":"스킬 사용 후, 공격이 가장 높은 같은 진영 아군 영웅의 공격을 <color=#82c07f>100%</color> 증가하며, 5초 동안 지속되고 중첩되지 않는다.","fullDesc":"스킬 사용 후, 공격이 가장 높은 같은 진영 아군 영웅의 공격을 <color=#82c07f>100%</color> 증가하며, 5초 동안 지속되고 중첩되지 않는다.","talentSkill":12011,"ultraSkill":2},{"id":9120205,"star":5,"shortDesc":"스킬 사용 후, 공격이 가장 높은 같은 진영 아군 영웅의 공격을 <color=#82c07f>100%</color> 증가하며, 5초 동안 지속되고 중첩되지 않는다.","fullDesc":"스킬 사용 후, 공격이 가장 높은 같은 진영 아군 영웅의 공격을 <color=#82c07f>100%</color> 증가하며, 5초 동안 지속되고 중첩되지 않는다.","talentSkill":12011,"ultraSkill":2},{"id":9120206,"star":6,"shortDesc":"스킬 사용 후, 공격이 가장 높은 같은 진영 아군 영웅의 공격을 <color=#82c07f>100%</color> 증가하며, 5초 동안 지속되고 중첩되지 않는다.","fullDesc":"스킬 사용 후, 공격이 가장 높은 같은 진영 아군 영웅의 공격을 <color=#82c07f>100%</color> 증가하며, 5초 동안 지속되고 중첩되지 않는다.","talentSkill":12011,"ultraSkill":2},{"id":9120207,"star":7,"shortDesc":"스킬 사용 후, 공격이 가장 높은 같은 진영 아군 영웅의 공격을 <color=#82c07f>100%</color> 증가하며, 5초 동안 지속되고 중첩되지 않는다.","fullDesc":"스킬 사용 후, 공격이 가장 높은 같은 진영 아군 영웅의 공격을 <color=#82c07f>100%</color> 증가하며, 5초 동안 지속되고 중첩되지 않는다.","talentSkill":12011,"ultraSkill":2},{"id":9120208,"star":8,"shortDesc":"스킬 사용 후, 공격이 가장 높은 같은 진영 아군 영웅의 공격을 <color=#82c07f>100%</color> 증가하며, 5초 동안 지속되고 중첩되지 않는다.","fullDesc":"스킬 사용 후, 공격이 가장 높은 같은 진영 아군 영웅의 공격을 <color=#82c07f>100%</color> 증가하며, 5초 동안 지속되고 중첩되지 않는다.","talentSkill":12011,"ultraSkill":2},{"id":9120209,"star":9,"shortDesc":"스킬 사용 후, 공격이 가장 높은 같은 진영 아군 영웅의 공격을 <color=#82c07f>100%</color> 증가하며, 5초 동안 지속되고 중첩되지 않는다.","fullDesc":"스킬 사용 후, 공격이 가장 높은 같은 진영 아군 영웅의 공격을 <color=#82c07f>100%</color> 증가하며, 5초 동안 지속되고 중첩되지 않는다.","talentSkill":12011,"ultraSkill":2}],"gear":null,"skins":[{"id":7912020,"belongHero":91202,"isDefault":false,"name":"물 슬라임","desc":"","quality":2,"cardAsset":"role_91202","iconAsset":"icon_hero_91202","paintingAsset":"role_91202","bgAsset":"bg_91202","harmonyCardAsset":null,"harmonyPaintingAsset":null,"harmonyBgAsset":"bg_91202","cardUrl":"/img/63d0711f93f66fe6ae50941277c0271a/Texture2D_role_91202.webp","isCurrent":true}],"skillsWithIcon":[{"id":2,"name":"텅 빈 머리","des":"머리가 텅 비어 아무것도 생각나지 않는다.","iconAsset":"icon_job_1001","typeLabel":"강화 2","iconUrl":"/img/e04a03308a91004f8db437a5ec6e60f6/Sprite_icon_job_1001.webp"},{"id":12011,"name":"원소의 힘","des":"자신의 피해 감소 <color=#79be6c>{0}%</color>가 증가한다.","iconAsset":"skillicon_12011","typeLabel":"강화 1","iconUrl":"/img/e947a8e0c02db9360ee3134c45865bcf/Sprite_skillicon_12011.webp"}]}